<baseDedados.CentralDeInformacoes>
  <todosOsClientes>
    <model.ClienteFisico>
      <nome>andrey</nome>
      <telefone>11111111111</telefone>
      <email>1@1</email>
      <CPF>78343724089</CPF>
    </model.ClienteFisico>
  </todosOsClientes>
  <todosOsFornecedores>
    <model.FornecedorFisico>
      <nome>Andrey</nome>
      <telefone>22222222222</telefone>
      <email>1@1</email>
      <cpfCnpj>78343724089</cpfCnpj>
      <servicos>
        <string>Buffet</string>
      </servicos>
      <quantContratosFisico>0</quantContratosFisico>
      <disponibilidade>true</disponibilidade>
    </model.FornecedorFisico>
    <model.FornecedorFisico>
      <nome>Joao</nome>
      <telefone>33333333333</telefone>
      <email>2@2</email>
      <cpfCnpj>46045664027</cpfCnpj>
      <servicos>
        <string>Buffet</string>
      </servicos>
      <quantContratosFisico>0</quantContratosFisico>
      <disponibilidade>true</disponibilidade>
    </model.FornecedorFisico>
    <model.FornecedorFisico>
      <nome>Ismael</nome>
      <telefone>33333333333</telefone>
      <email>3@3</email>
      <cpfCnpj>26216777033</cpfCnpj>
      <servicos>
        <string>Buffet</string>
      </servicos>
      <quantContratosFisico>0</quantContratosFisico>
      <disponibilidade>true</disponibilidade>
    </model.FornecedorFisico>
    <model.FornecedorFisico>
      <nome>Ana</nome>
      <telefone>44444444444</telefone>
      <email>4@4</email>
      <cpfCnpj>48829763071</cpfCnpj>
      <servicos>
        <string>Buffet</string>
      </servicos>
      <quantContratosFisico>0</quantContratosFisico>
      <disponibilidade>true</disponibilidade>
    </model.FornecedorFisico>
  </todosOsFornecedores>
  <todosEvento>
    <model.OrcamentoOuContrato>
      <clienteAssociado class="model.ClienteFisico" reference="../../../todosOsClientes/model.ClienteFisico"/>
      <nomeDoEvento>Evento para ver contrato</nomeDoEvento>
      <dataEHoraDoEvento>9000-12-12T00:00:00</dataEHoraDoEvento>
      <localDoEvento>novo</localDoEvento>
      <tamanho>102</tamanho>
      <foiContradoOuNao>true</foiContradoOuNao>
      <valor>3000</valor>
      <foiConcluido>false</foiConcluido>
      <comentariosFornecedores/>
      <fornecedores>
        <model.FornecedorFisico reference="../../../../todosOsFornecedores/model.FornecedorFisico"/>
        <model.FornecedorFisico reference="../../../../todosOsFornecedores/model.FornecedorFisico[2]"/>
        <model.FornecedorFisico reference="../../../../todosOsFornecedores/model.FornecedorFisico[3]"/>
        <model.FornecedorFisico reference="../../../../todosOsFornecedores/model.FornecedorFisico[4]"/>
      </fornecedores>
      <pacotesDeFornecedores/>
    </model.OrcamentoOuContrato>
    <model.OrcamentoOuContrato>
      <clienteAssociado class="model.ClienteFisico" reference="../../../todosOsClientes/model.ClienteFisico"/>
      <nomeDoEvento>Evento de excluir</nomeDoEvento>
      <dataEHoraDoEvento>5000-10-10T00:00:00</dataEHoraDoEvento>
      <localDoEvento>aaa</localDoEvento>
      <tamanho>00</tamanho>
      <foiContradoOuNao>true</foiContradoOuNao>
      <valor>0101</valor>
      <foiConcluido>true</foiConcluido>
      <comentariosFornecedores>
        <string>Andrey Agr vai</string>
        <string>Joao Vai mesmo</string>
        <string>Ismael Num falei</string>
      </comentariosFornecedores>
      <fornecedores>
        <model.FornecedorFisico reference="../../../../todosOsFornecedores/model.FornecedorFisico"/>
        <model.FornecedorFisico reference="../../../../todosOsFornecedores/model.FornecedorFisico[2]"/>
        <model.FornecedorFisico reference="../../../../todosOsFornecedores/model.FornecedorFisico[3]"/>
      </fornecedores>
      <pacotesDeFornecedores/>
    </model.OrcamentoOuContrato>
    <model.OrcamentoOuContrato>
      <clienteAssociado class="model.ClienteFisico" reference="../../../todosOsClientes/model.ClienteFisico"/>
      <nomeDoEvento>Evento que vou excluir o ultimo</nomeDoEvento>
      <dataEHoraDoEvento>5550-04-12T00:00:00</dataEHoraDoEvento>
      <localDoEvento>aqui</localDoEvento>
      <tamanho>10</tamanho>
      <foiContradoOuNao>true</foiContradoOuNao>
      <valor>1010</valor>
      <foiConcluido>true</foiConcluido>
      <comentariosFornecedores>
        <string>valeu</string>
        <string>tchau</string>
        <string>simbora</string>
      </comentariosFornecedores>
      <fornecedores>
        <model.FornecedorFisico reference="../../../../todosOsFornecedores/model.FornecedorFisico[4]"/>
        <model.FornecedorFisico reference="../../../../todosOsFornecedores/model.FornecedorFisico[3]"/>
        <model.FornecedorFisico reference="../../../../todosOsFornecedores/model.FornecedorFisico"/>
      </fornecedores>
      <pacotesDeFornecedores/>
    </model.OrcamentoOuContrato>
    <model.OrcamentoOuContrato>
      <clienteAssociado class="model.ClienteFisico" reference="../../../todosOsClientes/model.ClienteFisico"/>
      <nomeDoEvento>agr fudeu msm</nomeDoEvento>
      <dataEHoraDoEvento>4000-12-12T10:10:00</dataEHoraDoEvento>
      <localDoEvento>oxi</localDoEvento>
      <tamanho>1</tamanho>
      <foiContradoOuNao>false</foiContradoOuNao>
      <valor>1</valor>
      <foiConcluido>true</foiConcluido>
      <comentariosFornecedores>
        <string>Massa</string>
        <string>Beleza</string>
        <string>Valeu</string>
        <string>Ta bom</string>
      </comentariosFornecedores>
      <fornecedores>
        <model.FornecedorFisico reference="../../../../todosOsFornecedores/model.FornecedorFisico"/>
        <model.FornecedorFisico reference="../../../../todosOsFornecedores/model.FornecedorFisico[2]"/>
        <model.FornecedorFisico reference="../../../../todosOsFornecedores/model.FornecedorFisico[3]"/>
        <model.FornecedorFisico reference="../../../../todosOsFornecedores/model.FornecedorFisico[4]"/>
      </fornecedores>
      <pacotesDeFornecedores/>
    </model.OrcamentoOuContrato>
    <model.OrcamentoOuContrato>
      <clienteAssociado class="model.ClienteFisico" reference="../../../todosOsClientes/model.ClienteFisico"/>
      <nomeDoEvento>Evento 1</nomeDoEvento>
      <dataEHoraDoEvento>4000-12-12T00:00:00</dataEHoraDoEvento>
      <localDoEvento>n sei</localDoEvento>
      <tamanho>10</tamanho>
      <foiContradoOuNao>true</foiContradoOuNao>
      <valor>10</valor>
      <foiConcluido>false</foiConcluido>
      <fornecedores/>
      <pacotesDeFornecedores/>
    </model.OrcamentoOuContrato>
  </todosEvento>
  <todosServicos>
    <string>Buffet</string>
    <string>Musica</string>
    <string>Ornamentação</string>
    <string>Local</string>
    <string>Segurança</string>
    <string>Serviços Gerais</string>
    <string>Agente de publicidade</string>
    <string>Recepção</string>
  </todosServicos>
  <todosOsPacotes/>
  <administrador>
    <nome>Andrey</nome>
    <sobrenome>Andrey</sobrenome>
    <email>1@1</email>
    <senha>12345678</senha>
  </administrador>
</baseDedados.CentralDeInformacoes>